{"danceability":[0.456],"energy":[0.977],"key":[7],"loudness":[-4.603],"mode":[1],"speechiness":[0.0786],"acousticness":[0.126],"instrumentalness":[0.541],"liveness":[0.128],"valence":[0.577],"tempo":[96.307],"type":["audio_features"],"id":["32VPND9HN4aQXhGxqPPQQx"],"uri":["spotify:track:32VPND9HN4aQXhGxqPPQQx"],"track_href":["https://api.spotify.com/v1/tracks/32VPND9HN4aQXhGxqPPQQx"],"analysis_url":["https://api.spotify.com/v1/audio-analysis/32VPND9HN4aQXhGxqPPQQx"],"duration_ms":[444173],"time_signature":[4]}
