{"danceability":[0.549],"energy":[0.721],"key":[2],"loudness":[-7.346],"mode":[1],"speechiness":[0.0548],"acousticness":[0.208],"instrumentalness":[2.13e-006],"liveness":[0.126],"valence":[0.65],"tempo":[120.045],"type":["audio_features"],"id":["50swsZLMizT5UAdM5RhAhX"],"uri":["spotify:track:50swsZLMizT5UAdM5RhAhX"],"track_href":["https://api.spotify.com/v1/tracks/50swsZLMizT5UAdM5RhAhX"],"analysis_url":["https://api.spotify.com/v1/audio-analysis/50swsZLMizT5UAdM5RhAhX"],"duration_ms":[227396],"time_signature":[4]}
